airscape/__init__.py
airscape/const.py
airscape/exceptions.py
airscape-0.1.9.4.1.dist-info/LICENSE
airscape-0.1.9.4.1.dist-info/METADATA
airscape-0.1.9.4.1.dist-info/WHEEL
airscape-0.1.9.4.1.dist-info/top_level.txt
airscape-0.1.9.4.1.dist-info/RECORD
