Metadata-Version: 2.1
Name: airscape
Version: 0.1.9.4.1
Summary: An interface to control an AirScape Whole House Fan
Home-page: https://github.com/quielb/pypi-airscape
Author: Barry Quiel
Author-email: barry.quiel@gmail.com
License: GPL
Platform: UNKNOWN
Classifier: License :: OSI Approved :: GNU General Public License v3 (GPLv3)
Classifier: Programming Language :: Python :: 3
Classifier: Operating System :: OS Independent
License-File: LICENSE
Requires-Dist: requests
